{
    "address": "VAPA Cau Giay",
    "applicantIdDate": 1483203600000,
    "applicantIdNo": "432314321",
    "applicantIdType": "citizen",
    "applicantName": "Vu Dang Khoa",
    "applicantNote": "",
    "briefNote": "",
    "cachedModel": false,
    "cancellingDate": null,
    "cityCode": "01",
    "cityName": "Hà Nội",
    "columnBitmask": "0",
    "companyId": "20116",
    "contactEmail": "khoavd.it@gmail.com",
    "contactName": "VU DANG KHOA",
    "contactTelNo": "09876543456",
    "correcttingDate": null,
    "counter": 13,
    "createDate": 1527581701731,
    "delegateAddress": "VAPA Cau Giay",
    "delegateCityCode": "01",
    "delegateCityName": "Hà Nội",
    "delegateDistrictCode": "001",
    "delegateDistrictName": "Quận Ba Đình",
    "delegateEmail": "",
    "delegateIdNo": "432314321",
    "delegateName": "Vu Dang Khoa",
    "delegateTelNo": "09876543456",
    "delegateWardCode": "00001",
    "delegateWardName": "Phường Phúc Xá",
    "districtCode": "001",
    "districtName": "Quận Ba Đình",
    "dossierActionId": "0",
    "dossierId": "57802",
    "dossierNo": "TN-101",
    "dossierNote": "",
    "dossierRegister": "POUJRPHLYM",
    "dossierStatus": "",
    "dossierStatusText": "",
    "dossierSubStatus": "",
    "dossierSubStatusText": "",
    "dossierTemplateName": "",
    "dossierTemplateNo": "101-TPN2",
    "dueDate": 1528100101731,
    "endorsementDate": null,
    "entityCacheEnabled": true,
    "escapedModel": false,
    "extendDate": null,
    "finderCacheEnabled": true,
    "finishDate": null,
    "folderId": "0",
    "govAgencyCode": "TCTDTT",
    "govAgencyName": "Tổng cục Thể dục thể thao",
    "groupId": "55301",
    "lockState": "",
    "modelClass": "org.opencps.dossiermgt.model.Dossier",
    "modelClassName": "org.opencps.dossiermgt.model.Dossier",
    "modifiedDate": 1527581701731,
    "new": false,
    "notification": false,
    "online": false,
    "original": false,
    "originalCompanyId": "20116",
    "originalDossierId": "57802",
    "originalDossierStatus": "",
    "originalDossierTemplateNo": "",
    "originalGovAgencyCode": "TCTDTT",
    "originalGroupId": "55301",
    "originalReferenceUid": "6caa3f54-86ac-144d-60e5-d9721a8a74f8",
    "originalServiceCode": "TT68_BVHTTDL",
    "originalUserId": "0",
    "originalUuid": "866e550c-49e1-87a2-e642-a28136d8b6a7",
    "password": "0E6KUDTJ",
    "postalAddress": "",
    "postalCityCode": "01",
    "postalCityName": "",
    "postalDistrictCode": "03",
    "postalDistrictName": "",
    "postalServiceCode": "",
    "postalServiceName": "",
    "postalTelNo": "",
    "postalWardCode": "05",
    "postalWardName": "",
    "primaryKey": "57802",
    "primaryKeyObj": "57802",
    "receiveDate": 1527581701731,
    "referenceUid": "6caa3f54-86ac-144d-60e5-d9721a8a74f8",
    "releaseDate": null,
    "serverNo": "",
    "serviceCode": "TT68_BVHTTDL",
    "serviceName": "Đăng cai tổ chức Giải thi đấu vô địch quốc gia, giải trẻ quốc gia hàng năm từng môn thể thao",
    "stagedModelType": {
        "className": "org.opencps.dossiermgt.model.Dossier",
        "classNameId": "36201",
        "classSimpleName": "Dossier",
        "referrerClassName": null,
        "referrerClassNameId": "0"
    },
    "processOptionId": "101-PRCID2",
    "submissionNote": "",
    "submitDate": null,
    "submitting": false,
    "userId": "0",
    "userName": "",
    "userUuid": "",
    "uuid": "866e550c-49e1-87a2-e642-a28136d8b6a7",
    "viaPostal": 0,
    "wardCode": "00001",
    "wardName": "Phường Phúc Xá"
}